jude/__init__.py
jude/cli.py
jude/jude.py
jude-0.1.0.dist-info/DESCRIPTION.rst
jude-0.1.0.dist-info/METADATA
jude-0.1.0.dist-info/RECORD
jude-0.1.0.dist-info/WHEEL
jude-0.1.0.dist-info/entry_points.txt
jude-0.1.0.dist-info/metadata.json
jude-0.1.0.dist-info/top_level.txt
