Metadata-Version: 2.0
Name: jude
Version: 0.1.0
Summary: Hey Jude, don't make it bad Take a sad song and make it better.
Home-page: https://github.com/imohitawasthi/jude
Author: Mohit Awasthi
Author-email: imohitawasthi@gmail.com
License: Apache Software License 2.0
Keywords: jude
Platform: UNKNOWN
Classifier: Development Status :: 2 - Pre-Alpha
Classifier: Intended Audience :: Developers
Classifier: License :: OSI Approved :: Apache Software License
Classifier: Natural Language :: English
Classifier: Programming Language :: Python :: 2.7
Classifier: Programming Language :: Python :: 3
Classifier: Programming Language :: Python :: 3.4
Classifier: Programming Language :: Python :: 3.5
Classifier: Programming Language :: Python :: 3.6
Classifier: Programming Language :: Python :: 3.7
Requires-Dist: Click (>=6.0)
